vais_mcp/__init__.py
vais_mcp/config.py
vais_mcp/google_cloud.py
vais_mcp/server.py
vais_mcp/vais.py
vais_mcp-1.0.0.dist-info/METADATA
vais_mcp-1.0.0.dist-info/WHEEL
vais_mcp-1.0.0.dist-info/entry_points.txt
vais_mcp-1.0.0.dist-info/licenses/LICENSE
vais_mcp-1.0.0.dist-info/RECORD
