Metadata-Version: 2.4
Name: vais_mcp
Version: 1.0.0
Summary: MCP server to search private data in Vertex AI Search.
Author-email: Shintaro Mormioto <mrmtsntr1@gmail.com>
License: Apache-2.0
License-File: LICENSE
Classifier: License :: OSI Approved :: Apache Software License
Classifier: Programming Language :: Python :: 3
Classifier: Programming Language :: Python :: 3.13
Requires-Python: >=3.13
Requires-Dist: fastmcp>=2.3.3
Requires-Dist: google-cloud-discoveryengine>=0.13.8
Requires-Dist: loguru>=0.7.3
Requires-Dist: mcp[cli]>=1.8.0
Requires-Dist: pytest>=8.3.5
Requires-Dist: uvicorn>=0.34.2
Provides-Extra: dev
Requires-Dist: ruff>=0.11.8; extra == 'dev'
